odoo8_addon_website_seo_redirection-8.0.1.1.0-py2.7-nspkg.pth
odoo_addons/website_seo_redirection/__openerp__.py
odoo_addons/website_seo_redirection/__init__.py
odoo_addons/website_seo_redirection/exceptions.py
odoo_addons/website_seo_redirection/README.rst
odoo_addons/website_seo_redirection/security/ir.model.access.csv
odoo_addons/website_seo_redirection/migrations/8.0.1.1.0/pre-migrate.py
odoo_addons/website_seo_redirection/l10n/es.po
odoo_addons/website_seo_redirection/models/website_seo_redirection.py
odoo_addons/website_seo_redirection/models/__init__.py
odoo_addons/website_seo_redirection/models/ir_http.py
odoo_addons/website_seo_redirection/models/website.py
odoo_addons/website_seo_redirection/i18n/ru.po
odoo_addons/website_seo_redirection/i18n/it.po
odoo_addons/website_seo_redirection/i18n/es.po
odoo_addons/website_seo_redirection/i18n/ca.po
odoo_addons/website_seo_redirection/i18n/sl.po
odoo_addons/website_seo_redirection/i18n/de.po
odoo_addons/website_seo_redirection/i18n/fr.po
odoo_addons/website_seo_redirection/i18n/pt_BR.po
odoo_addons/website_seo_redirection/i18n/el_GR.po
odoo_addons/website_seo_redirection/views/website_seo_redirection_view.xml
odoo_addons/website_seo_redirection/views/assets.xml
odoo_addons/website_seo_redirection/tests/test_model_website_seo_redirection.py
odoo_addons/website_seo_redirection/tests/test_model_website.py
odoo_addons/website_seo_redirection/tests/__init__.py
odoo_addons/website_seo_redirection/tests/test_ui.py
odoo_addons/website_seo_redirection/demo/website_seo_redirection_demo.xml
odoo_addons/website_seo_redirection/static/description/icon.png
odoo_addons/website_seo_redirection/static/src/js/website_seo_redirection.tour.js
odoo_addons/website_seo_redirection/static/src/js/website_seo.js
odoo_addons/website_seo_redirection/static/src/xml/website_seo.xml
odoo8_addon_website_seo_redirection-8.0.1.1.0.dist-info/top_level.txt
odoo8_addon_website_seo_redirection-8.0.1.1.0.dist-info/WHEEL
odoo8_addon_website_seo_redirection-8.0.1.1.0.dist-info/RECORD
odoo8_addon_website_seo_redirection-8.0.1.1.0.dist-info/metadata.json
odoo8_addon_website_seo_redirection-8.0.1.1.0.dist-info/DESCRIPTION.rst
odoo8_addon_website_seo_redirection-8.0.1.1.0.dist-info/METADATA
odoo8_addon_website_seo_redirection-8.0.1.1.0.dist-info/namespace_packages.txt
