Metadata-Version: 2.0
Name: odoo8-addon-website-seo-redirection
Version: 8.0.1.1.0
Summary: Redirect any controller to the URL of your dreams
Home-page: https://tecnativa.com/
Author: UNKNOWN
Author-email: UNKNOWN
License: LGPL-3
Platform: UNKNOWN
Requires-Dist: odoo (<9.0a,>=8.0a)
Classifier: Programming Language :: Python :: 2.7
Classifier: Framework :: Odoo
Classifier: License :: OSI Approved :: GNU Lesser General Public License v3 (LGPLv3)
